pixy/__init__.py
pixy/client.py
pixy/schemas.py
pixy/settings.py
pixy/utils.py
pixy_sdk-0.0.9.dist-info/METADATA
pixy_sdk-0.0.9.dist-info/WHEEL
pixy_sdk-0.0.9.dist-info/entry_points.txt
pixy_sdk-0.0.9.dist-info/top_level.txt
pixy_sdk-0.0.9.dist-info/RECORD
