Metadata-Version: 2.4
Name: pixy-sdk
Version: 0.0.9
Summary: A python sdk for pixy.
Author-email: Amirhossein Berenji <ahberenji@gmail.com>, Mahdi Kiani <mahdikiany@gmail.com>
Maintainer-email: Amirhossein Berenji <ahberenji@gmail.com>, Mahdi Kiani <mahdikiany@gmail.com>
Project-URL: Homepage, https://github.com/pixiee-ai/pixy-sdk
Project-URL: Bug Reports, https://github.com/pixiee-ai/pixy-sdk/issues
Project-URL: Funding, https://github.com/pixiee-ai/pixy-sdk
Project-URL: Say Thanks!, https://saythanks.io/to/mahdikiani
Project-URL: Source, https://github.com/pixiee-ai/pixy-sdk
Keywords: pixy,GenAI,Image Generation,Subtitle,Video Generation
Classifier: Development Status :: 3 - Alpha
Classifier: Intended Audience :: Developers
Classifier: Topic :: Software Development :: Build Tools
Classifier: License :: OSI Approved :: MIT License
Classifier: Programming Language :: Python :: 3
Classifier: Programming Language :: Python :: 3.10
Classifier: Programming Language :: Python :: 3.11
Classifier: Programming Language :: Python :: 3.12
Classifier: Programming Language :: Python :: 3 :: Only
Requires-Python: >=3.9
Requires-Dist: pydantic>=2
Requires-Dist: httpx
